sinapsis_easyocr/__init__.py
sinapsis_easyocr/helpers/__init__.py
sinapsis_easyocr/helpers/tags.py
sinapsis_easyocr/templates/__init__.py
sinapsis_easyocr/templates/easy_ocr.py
sinapsis_easyocr-0.1.9.dist-info/licenses/LICENSE
sinapsis_easyocr-0.1.9.dist-info/METADATA
sinapsis_easyocr-0.1.9.dist-info/WHEEL
sinapsis_easyocr-0.1.9.dist-info/top_level.txt
sinapsis_easyocr-0.1.9.dist-info/RECORD
