Metadata-Version: 2.4
Name: sinapsis-easyocr
Version: 0.1.9
Summary: Perform optical character recognition using the EasyOCR library
Author-email: SinapsisAI <dev@sinapsis.tech>
Project-URL: Homepage, https://sinapsis.tech
Project-URL: Documentation, https://docs.sinapsis.tech/docs
Project-URL: Tutorials, https://docs.sinapsis.tech/tutorials
Project-URL: Repository, https://github.com/Sinapsis-AI/sinapsis-ocr.git
Requires-Python: >=3.10
License-File: LICENSE
Requires-Dist: easyocr>=1.7.2
Requires-Dist: opencv-python-headless>=4.11.0.86
Requires-Dist: scikit-learn>=1.6.1
Requires-Dist: sinapsis>=0.1.1
Provides-Extra: sinapsis-data-readers
Requires-Dist: sinapsis-data-readers[opencv]>=0.1.0; extra == "sinapsis-data-readers"
Provides-Extra: sinapsis-data-writers
Requires-Dist: sinapsis-data-writers>=0.1.0; extra == "sinapsis-data-writers"
Provides-Extra: sinapsis-data-visualization
Requires-Dist: sinapsis-data-visualization[visualization-matplotlib]>=0.1.0; extra == "sinapsis-data-visualization"
Provides-Extra: all
Requires-Dist: sinapsis-easyocr[sinapsis-data-readers,sinapsis-data-visualization,sinapsis-data-writers]; extra == "all"
Dynamic: license-file
